conda_quetz_auth/__init__.py
conda_quetz_auth/constants.py
conda_quetz_auth/exceptions.py
conda_quetz_auth/plugin.py
conda_quetz_auth/handlers/__init__.py
conda_quetz_auth/handlers/token.py
conda_dpauth-1.0.0.dist-info/METADATA
conda_dpauth-1.0.0.dist-info/WHEEL
conda_dpauth-1.0.0.dist-info/top_level.txt
conda_dpauth-1.0.0.dist-info/RECORD
