Metadata-Version: 2.1
Name: conda-dpauth
Version: 1.0.0
Summary: Conda plugin for quetz to authenticate users
Requires-Python: >=3.9
Requires-Dist: conda
